whisper_normalizer/__init__.py
whisper_normalizer/_modidx.py
whisper_normalizer/basic.py
whisper_normalizer/core.py
whisper_normalizer/english.py
whisper_normalizer/english_normalizer.py
whisper_normalizer/indic_normalizer.py
whisper_normalizer/langinfo.py
whisper_normalizer_offline-0.0.13.dist-info/LICENSE
whisper_normalizer_offline-0.0.13.dist-info/METADATA
whisper_normalizer_offline-0.0.13.dist-info/WHEEL
whisper_normalizer_offline-0.0.13.dist-info/entry_points.txt
whisper_normalizer_offline-0.0.13.dist-info/top_level.txt
whisper_normalizer_offline-0.0.13.dist-info/RECORD
