Metadata-Version: 2.1
Name: whisper_normalizer_offline
Version: 0.0.13
Summary: A python package for whisper normalizer
Home-page: https://github.com/fabrizio8/whisper_normalizer
Author: kurianbenoy
Author-email: fabsec@pm.me
License: MIT License
Keywords: nbdev jupyter notebook openai whisper normalizer
Classifier: Development Status :: 4 - Beta
Classifier: Intended Audience :: Developers
Classifier: Natural Language :: English
Classifier: Programming Language :: Python :: 3.7
Classifier: Programming Language :: Python :: 3.8
Classifier: Programming Language :: Python :: 3.9
Classifier: Programming Language :: Python :: 3.10
Classifier: License :: OSI Approved :: MIT License
Requires-Python: >=3.7
License-File: LICENSE
Requires-Dist: more_itertools
Requires-Dist: regex
Provides-Extra: dev
Requires-Dist: black; extra == "dev"
Requires-Dist: nbdev; extra == "dev"
